MANIFEST.in
README.md
setup.py
requestions/__init__.py
requestions/httpetrified.py
requestions/io.py
requestions/utils.py
requestions.egg-info/PKG-INFO
requestions.egg-info/SOURCES.txt
requestions.egg-info/dependency_links.txt
requestions.egg-info/not-zip-safe
requestions.egg-info/requires.txt
requestions.egg-info/top_level.txt